ipywidget_chatbot/__init__.py
ipywidget_chatbot-0.1.2.dist-info/METADATA
ipywidget_chatbot-0.1.2.dist-info/WHEEL
ipywidget_chatbot-0.1.2.dist-info/top_level.txt
ipywidget_chatbot-0.1.2.dist-info/RECORD
