Metadata-Version: 2.4
Name: ipywidget-chatbot
Version: 0.1.2
Summary: Add your description here
Requires-Python: >=3.10
Requires-Dist: ipywidgets>=8.1.7
